nengo_gui/__init__.py
nengo_gui/compat.py
nengo_gui/completion.py
nengo_gui/config.py
nengo_gui/conftest.py
nengo_gui/exec_env.py
nengo_gui/gui.py
nengo_gui/guibackend.py
nengo_gui/ipython.py
nengo_gui/jupyter.py
nengo_gui/layout.py
nengo_gui/main.py
nengo_gui/modal_js.py
nengo_gui/namefinder.py
nengo_gui/nossl.py
nengo_gui/page.py
nengo_gui/password.py
nengo_gui/seed_generation.py
nengo_gui/server.py
nengo_gui/static_plots.py
nengo_gui/testing_tools.py
nengo_gui/url.py
nengo_gui/user_action.py
nengo_gui/version.py
nengo_gui/viz.py
nengo_gui/_vendor/README.rst
nengo_gui/_vendor/__init__.py
nengo_gui/_vendor/cookies.py
nengo_gui/_vendor/requirements.txt
nengo_gui/_vendor/test_cookies.py
nengo_gui/components/__init__.py
nengo_gui/components/ace_editor.py
nengo_gui/components/component.py
nengo_gui/components/editor.py
nengo_gui/components/htmlview.py
nengo_gui/components/netgraph.py
nengo_gui/components/pointer.py
nengo_gui/components/progress.py
nengo_gui/components/raster.py
nengo_gui/components/sim_control.py
nengo_gui/components/slider.py
nengo_gui/components/spa_plot.py
nengo_gui/components/spa_similarity.py
nengo_gui/components/spike_grid.py
nengo_gui/components/value.py
nengo_gui/components/voltage.py
nengo_gui/components/xyvalue.py
nengo_gui/examples/default.py
nengo_gui/examples/default.py.cfg
nengo_gui/examples/basics/2d_representation.py
nengo_gui/examples/basics/addition.py
nengo_gui/examples/basics/combining.py
nengo_gui/examples/basics/communication_channel.py
nengo_gui/examples/basics/ensemble_array.py
nengo_gui/examples/basics/html.py
nengo_gui/examples/basics/html.py.cfg
nengo_gui/examples/basics/inhibitory_gating.py
nengo_gui/examples/basics/many_neurons.py
nengo_gui/examples/basics/multiplication.py
nengo_gui/examples/basics/single_neuron.py
nengo_gui/examples/basics/squaring.py
nengo_gui/examples/basics/two_neurons.py
nengo_gui/examples/hbb_tutorials/read_me.py
nengo_gui/examples/hbb_tutorials/chapter1/singleneuron.py
nengo_gui-0.6.0.dist-info/licenses/LICENSE.rst
nengo_gui-0.6.0.dist-info/METADATA
nengo_gui-0.6.0.dist-info/WHEEL
nengo_gui-0.6.0.dist-info/entry_points.txt
nengo_gui-0.6.0.dist-info/top_level.txt
nengo_gui-0.6.0.dist-info/RECORD
