Metadata-Version: 2.4
Name: nengo-gui
Version: 0.6.0
Summary: Web-based GUI for building and visualizing Nengo models.
Home-page: https://github.com/nengo/nengo-gui
Author: Applied Brain Research
Author-email: info@appliedbrainresearch.com
License: GNU General Public License, version 2
Classifier: Development Status :: 5 - Production/Stable
Classifier: Intended Audience :: Science/Research
Classifier: License :: OSI Approved :: GNU General Public License v2 (GPLv2)
Classifier: Operating System :: OS Independent
Classifier: Programming Language :: JavaScript
Classifier: Programming Language :: Python :: 2.7
Classifier: Programming Language :: Python :: 3.4
Classifier: Programming Language :: Python :: 3.5
Classifier: Topic :: Scientific/Engineering :: Artificial Intelligence
License-File: LICENSE.rst
Requires-Dist: nengo>=2.6.0
Dynamic: author
Dynamic: author-email
Dynamic: classifier
Dynamic: description
Dynamic: home-page
Dynamic: license
Dynamic: license-file
Dynamic: requires-dist
Dynamic: summary
